CHANGELOG.md
LICENSE
raider/__init__.py
raider/__version__.py
raider/cli.py
raider/config.py
raider/flow.py
raider/flowgraph.py
raider/flowstore.py
raider/fuzzing.py
raider/logger.py
raider/macros.hy
raider/operations.py
raider/parsers/config.py
raider/parsers/delete.py
raider/parsers/edit.py
raider/parsers/inspect.py
raider/parsers/new.py
raider/parsers/run.py
raider/parsers/shell.py
raider/parsers/show.py
raider/plugins/__init__.py
raider/plugins/basic/__init__.py
raider/plugins/basic/command.py
raider/plugins/basic/cookie.py
raider/plugins/basic/file.py
raider/plugins/basic/header.py
raider/plugins/basic/html.py
raider/plugins/basic/jsonp.py
raider/plugins/basic/prompt.py
raider/plugins/basic/regex.py
raider/plugins/basic/variable.py
raider/plugins/common.py
raider/plugins/modifiers.py
raider/plugins/parsers.py
raider/plugins/processors.py
raider/projects.py
raider/raider.py
raider/request.py
raider/search.py
raider/structures.py
raider/user.py
raider/utils.py
raider-0.3.3.dist-info/LICENSE
raider-0.3.3.dist-info/METADATA
raider-0.3.3.dist-info/WHEEL
raider-0.3.3.dist-info/entry_points.txt
raider-0.3.3.dist-info/RECORD
