Metadata-Version: 2.1
Name: raider
Version: 0.3.3
Summary: OWASP Raider: a novel framework for manipulating the HTTP processes of persistent sessions.
Home-page: https://raiderauth.com/
License: GPL-3.0-or-later
Keywords: authentication,authorization,finite-state-machine,fsm,hy,hylang,lisp,owasp,python,raider,raiderauth,security
Author: Daniel Neagaru
Author-email: daniel@digeex.de
Requires-Python: >=3.8,<3.11
Classifier: Development Status :: 4 - Beta
Classifier: Environment :: Console
Classifier: Intended Audience :: Developers
Classifier: Intended Audience :: Information Technology
Classifier: Intended Audience :: System Administrators
Classifier: License :: OSI Approved :: GNU General Public License v3 or later (GPLv3+)
Classifier: Natural Language :: English
Classifier: Operating System :: POSIX :: Linux
Classifier: Programming Language :: Lisp
Classifier: Programming Language :: Python :: 3
Classifier: Programming Language :: Python :: 3.8
Classifier: Programming Language :: Python :: 3.9
Classifier: Programming Language :: Python :: 3.10
Classifier: Programming Language :: Python :: 3.10
Classifier: Programming Language :: Python :: 3.8
Classifier: Programming Language :: Python :: 3.9
Classifier: Topic :: Internet :: WWW/HTTP
Classifier: Topic :: Security
Classifier: Topic :: Software Development :: Libraries :: Python Modules
Classifier: Topic :: Software Development :: Testing
Requires-Dist: bs4 (>=0.0.1,<0.0.2)
Requires-Dist: funcparserlib (>=1.0.0a0,<2.0.0)
Requires-Dist: hy (>=1.0.a4,<2.0)
Requires-Dist: igraph (>=0.10.2,<0.11.0)
Requires-Dist: ipython (>=8.4.0,<9.0.0)
Requires-Dist: pkce (>=1.0.3,<2.0.0)
Requires-Dist: requests (>=2.25.1,<3.0.0)
Requires-Dist: requests-toolbelt (>=0.10.1,<0.11.0)
Project-URL: Documentation, https://docs.raiderauth.com/en/latest/
Project-URL: Repository, https://github.com/OWASP/raider
